[
    {
        "firstName":"Prad",
        "lastName":"Pitt",
        "birthday":"12-18-1963",
        "image":"https://m.media-amazon.com/images/M/MV5BMjA1MjE2MTQ2MV5BMl5BanBnXkFtZTcwMjE5MDY0Nw@@._V1_UX214_CR0,0,214,317_AL_.jpg",
        "link":"https://www.imdb.com/name/nm0000093/?ref_=nm_mv_close#actor"
    },    
    {
        "firstName":"Pedro",
        "lastName":"Pascal",
        "birthday":"04-02-1975",
        "image":"https://m.media-amazon.com/images/M/MV5BYzQ5Yzg1NzktMDcxNC00ZDc1LWJlMjEtNTg2ZjRlOTk4ZDNjXkEyXkFqcGdeQXVyODk4OTc3MTY@._V1_UY317_CR5,0,214,317_AL_.jpg",        
        "link": "https://www.imdb.com/name/nm0050959/?ref_=nv_sr_srsg_0"
    },
    {
        "firstName":"Julia",
        "lastName":"Louis-Dreyfus",
        "birthday":"01-13-1961",
        "image":"https://m.media-amazon.com/images/M/MV5BMTYzMDM2MTg2Nl5BMl5BanBnXkFtZTcwODQ0OTA1Mg@@._V1_UY317_CR7,0,214,317_AL_.jpg",        
        "link": "https://www.imdb.com/name/nm0000506/?ref_=tt_ov_st_sm"
    },
    {
        "firstName":"Larry",
        "lastName":"David",
        "birthday":"07-02-1947",
        "image":"https://m.media-amazon.com/images/M/MV5BMTg1Njg4MzQxNV5BMl5BanBnXkFtZTcwNDgzNDUwMw@@._V1_UY317_CR7,0,214,317_AL_.jpg",        
        "link":"https://www.imdb.com/name/nm0202970/?ref_=nv_sr_srsg_0"
    },
    {
        "firstName":"Angelina",
        "lastName":"Jolie",
        "birthday":"06-04-1975",
        "image":"https://m.media-amazon.com/images/M/MV5BODg3MzYwMjE4N15BMl5BanBnXkFtZTcwMjU5NzAzNw@@._V1_UY317_CR22,0,214,317_AL_.jpg",
        "link":"https://www.imdb.com/name/nm0001401/?ref_=nv_sr_srsg_3"
    },
    {
        "firstName":"Elisabeth",
        "lastName":"Moss",
        "birthday":"07-24-1982",
        "image":"https://m.media-amazon.com/images/M/MV5BNTMwMDg1MDkyNV5BMl5BanBnXkFtZTcwNzEwMzg1Nw@@._V1_UY317_CR131,0,214,317_AL_.jpg",        
        "link": "https://www.imdb.com/name/nm0005253/?ref_=nv_sr_srsg_3"
    }
]

